<annotation>
	<folder>files</folder>
	<filename>C115_D2_P2.jpg</filename>
	<path>./files/C115_D2_P2.jpg</path>
	<source>
		<database>Unknown</database>
	</source>
	<size>
		<width>1392</width>
		<height>1042</height>
		<depth>3</depth>
	</size>
	<segmented>0</segmented>
	<object>
		<name>junction</name>
		<pose>Unspecified</pose>
		<truncated>0</truncated>
		<difficult>0</difficult>
		<bndbox>
			<xmin>1031</xmin>
			<ymin>746</ymin>
			<xmax>1055</xmax>
			<ymax>769</ymax>
		</bndbox>
	</object>
	<object>
		<name>text</name>
		<pose>Unspecified</pose>
		<truncated>0</truncated>
		<difficult>0</difficult>
		<bndbox>
			<xmin>1154</xmin>
			<ymin>583</ymin>
			<xmax>1214</xmax>
			<ymax>639</ymax>
		</bndbox>
	</object>
	<object>
		<name>resistor</name>
		<pose>Unspecified</pose>
		<truncated>0</truncated>
		<difficult>0</difficult>
		<bndbox>
			<xmin>543</xmin>
			<ymin>280</ymin>
			<xmax>739</xmax>
			<ymax>364</ymax>
		</bndbox>
	</object>
	<object>
		<name>text</name>
		<pose>Unspecified</pose>
		<truncated>0</truncated>
		<difficult>0</difficult>
		<bndbox>
			<xmin>986</xmin>
			<ymin>299</ymin>
			<xmax>1037</xmax>
			<ymax>343</ymax>
		</bndbox>
	</object>
	<object>
		<name>capacitor.unpolarized</name>
		<pose>Unspecified</pose>
		<truncated>0</truncated>
		<difficult>0</difficult>
		<bndbox>
			<xmin>1010</xmin>
			<ymin>567</ymin>
			<xmax>1137</xmax>
			<ymax>639</ymax>
		</bndbox>
	</object>
	<object>
		<name>junction</name>
		<pose>Unspecified</pose>
		<truncated>0</truncated>
		<difficult>0</difficult>
		<bndbox>
			<xmin>329</xmin>
			<ymin>279</ymin>
			<xmax>353</xmax>
			<ymax>305</ymax>
		</bndbox>
	</object>
	<object>
		<name>text</name>
		<pose>Unspecified</pose>
		<truncated>0</truncated>
		<difficult>0</difficult>
		<bndbox>
			<xmin>624</xmin>
			<ymin>216</ymin>
			<xmax>672</xmax>
			<ymax>269</ymax>
		</bndbox>
	</object>
	<object>
		<name>junction</name>
		<pose>Unspecified</pose>
		<truncated>0</truncated>
		<difficult>0</difficult>
		<bndbox>
			<xmin>276</xmin>
			<ymin>606</ymin>
			<xmax>291</xmax>
			<ymax>622</ymax>
		</bndbox>
	</object>
	<object>
		<name>inductor</name>
		<pose>Unspecified</pose>
		<truncated>0</truncated>
		<difficult>0</difficult>
		<bndbox>
			<xmin>904</xmin>
			<ymin>349</ymin>
			<xmax>1115</xmax>
			<ymax>430</ymax>
		</bndbox>
	</object>
	<object>
		<name>text</name>
		<pose>Unspecified</pose>
		<truncated>0</truncated>
		<difficult>0</difficult>
		<bndbox>
			<xmin>181</xmin>
			<ymin>373</ymin>
			<xmax>241</xmax>
			<ymax>449</ymax>
		</bndbox>
	</object>
	<object>
		<name>voltage.dc</name>
		<pose>Unspecified</pose>
		<truncated>0</truncated>
		<difficult>0</difficult>
		<bndbox>
			<xmin>232</xmin>
			<ymin>379</ymin>
			<xmax>404</xmax>
			<ymax>456</ymax>
		</bndbox>
	</object>
</annotation>
