<annotation>
	<folder>files</folder>
	<filename>C118_D1_P2.jpg</filename>
	<path>./files/C118_D1_P2.jpg</path>
	<source>
		<database>Unknown</database>
	</source>
	<size>
		<width>1392</width>
		<height>1042</height>
		<depth>3</depth>
	</size>
	<segmented>0</segmented>
	<object>
		<name>junction</name>
		<pose>Unspecified</pose>
		<truncated>0</truncated>
		<difficult>0</difficult>
		<bndbox>
			<xmin>742</xmin>
			<ymin>353</ymin>
			<xmax>773</xmax>
			<ymax>384</ymax>
		</bndbox>
	</object>
	<object>
		<name>text</name>
		<pose>Unspecified</pose>
		<truncated>0</truncated>
		<difficult>0</difficult>
		<bndbox>
			<xmin>907</xmin>
			<ymin>310</ymin>
			<xmax>1035</xmax>
			<ymax>387</ymax>
		</bndbox>
	</object>
	<object>
		<name>junction</name>
		<pose>Unspecified</pose>
		<truncated>0</truncated>
		<difficult>0</difficult>
		<bndbox>
			<xmin>758</xmin>
			<ymin>430</ymin>
			<xmax>794</xmax>
			<ymax>466</ymax>
		</bndbox>
	</object>
	<object>
		<name>junction</name>
		<pose>Unspecified</pose>
		<truncated>0</truncated>
		<difficult>0</difficult>
		<bndbox>
			<xmin>677</xmin>
			<ymin>229</ymin>
			<xmax>710</xmax>
			<ymax>259</ymax>
		</bndbox>
	</object>
	<object>
		<name>terminal</name>
		<pose>Unspecified</pose>
		<truncated>0</truncated>
		<difficult>0</difficult>
		<bndbox>
			<xmin>1166</xmin>
			<ymin>184</ymin>
			<xmax>1203</xmax>
			<ymax>209</ymax>
		</bndbox>
	</object>
	<object>
		<name>terminal</name>
		<pose>Unspecified</pose>
		<truncated>0</truncated>
		<difficult>0</difficult>
		<bndbox>
			<xmin>201</xmin>
			<ymin>617</ymin>
			<xmax>225</xmax>
			<ymax>639</ymax>
		</bndbox>
	</object>
	<object>
		<name>text</name>
		<pose>Unspecified</pose>
		<truncated>0</truncated>
		<difficult>0</difficult>
		<bndbox>
			<xmin>395</xmin>
			<ymin>378</ymin>
			<xmax>468</xmax>
			<ymax>434</ymax>
		</bndbox>
	</object>
	<object>
		<name>junction</name>
		<pose>Unspecified</pose>
		<truncated>0</truncated>
		<difficult>0</difficult>
		<bndbox>
			<xmin>720</xmin>
			<ymin>309</ymin>
			<xmax>742</xmax>
			<ymax>333</ymax>
		</bndbox>
	</object>
	<object>
		<name>text</name>
		<pose>Unspecified</pose>
		<truncated>0</truncated>
		<difficult>0</difficult>
		<bndbox>
			<xmin>459</xmin>
			<ymin>607</ymin>
			<xmax>575</xmax>
			<ymax>679</ymax>
		</bndbox>
	</object>
	<object>
		<name>terminal</name>
		<pose>Unspecified</pose>
		<truncated>0</truncated>
		<difficult>0</difficult>
		<bndbox>
			<xmin>228</xmin>
			<ymin>674</ymin>
			<xmax>262</xmax>
			<ymax>704</ymax>
		</bndbox>
	</object>
	<object>
		<name>terminal</name>
		<pose>Unspecified</pose>
		<truncated>0</truncated>
		<difficult>0</difficult>
		<bndbox>
			<xmin>79</xmin>
			<ymin>403</ymin>
			<xmax>118</xmax>
			<ymax>431</ymax>
		</bndbox>
	</object>
	<object>
		<name>or</name>
		<pose>Unspecified</pose>
		<truncated>0</truncated>
		<difficult>0</difficult>
		<bndbox>
			<xmin>241</xmin>
			<ymin>299</ymin>
			<xmax>485</xmax>
			<ymax>454</ymax>
		</bndbox>
	</object>
	<object>
		<name>terminal</name>
		<pose>Unspecified</pose>
		<truncated>0</truncated>
		<difficult>0</difficult>
		<bndbox>
			<xmin>131</xmin>
			<ymin>465</ymin>
			<xmax>151</xmax>
			<ymax>481</ymax>
		</bndbox>
	</object>
	<object>
		<name>nor</name>
		<pose>Unspecified</pose>
		<truncated>0</truncated>
		<difficult>0</difficult>
		<bndbox>
			<xmin>336</xmin>
			<ymin>511</ymin>
			<xmax>578</xmax>
			<ymax>670</ymax>
		</bndbox>
	</object>
	<object>
		<name>nand</name>
		<pose>Unspecified</pose>
		<truncated>0</truncated>
		<difficult>0</difficult>
		<bndbox>
			<xmin>843</xmin>
			<ymin>231</ymin>
			<xmax>1012</xmax>
			<ymax>351</ymax>
		</bndbox>
	</object>
</annotation>
