<annotation>
	<folder>files</folder>
	<filename>C38_D2_P2.jpg</filename>
	<path>./files/C38_D2_P2.jpg</path>
	<source>
		<database>Unknown</database>
	</source>
	<size>
		<width>2000</width>
		<height>1500</height>
		<depth>3</depth>
	</size>
	<segmented>0</segmented>
	<object>
		<name>transformer</name>
		<pose>Unspecified</pose>
		<truncated>0</truncated>
		<difficult>0</difficult>
		<bndbox>
			<xmin>362</xmin>
			<ymin>253</ymin>
			<xmax>508</xmax>
			<ymax>493</ymax>
		</bndbox>
	</object>
	<object>
		<name>diode</name>
		<pose>Unspecified</pose>
		<truncated>0</truncated>
		<difficult>0</difficult>
		<bndbox>
			<xmin>736</xmin>
			<ymin>144</ymin>
			<xmax>838</xmax>
			<ymax>212</ymax>
		</bndbox>
	</object>
	<object>
		<name>capacitor.unpolarized</name>
		<pose>Unspecified</pose>
		<truncated>0</truncated>
		<difficult>0</difficult>
		<bndbox>
			<xmin>990</xmin>
			<ymin>137</ymin>
			<xmax>1091</xmax>
			<ymax>192</ymax>
		</bndbox>
	</object>
	<object>
		<name>capacitor.unpolarized</name>
		<pose>Unspecified</pose>
		<truncated>0</truncated>
		<difficult>0</difficult>
		<bndbox>
			<xmin>1580</xmin>
			<ymin>675</ymin>
			<xmax>1699</xmax>
			<ymax>743</ymax>
		</bndbox>
	</object>
	<object>
		<name>terminal</name>
		<pose>Unspecified</pose>
		<truncated>0</truncated>
		<difficult>0</difficult>
		<bndbox>
			<xmin>1597</xmin>
			<ymin>796</ymin>
			<xmax>1685</xmax>
			<ymax>886</ymax>
		</bndbox>
	</object>
	<object>
		<name>crossover</name>
		<pose>Unspecified</pose>
		<truncated>0</truncated>
		<difficult>0</difficult>
		<bndbox>
			<xmin>1031</xmin>
			<ymin>273</ymin>
			<xmax>1051</xmax>
			<ymax>294</ymax>
		</bndbox>
	</object>
	<object>
		<name>crossover</name>
		<pose>Unspecified</pose>
		<truncated>0</truncated>
		<difficult>0</difficult>
		<bndbox>
			<xmin>1443</xmin>
			<ymin>273</ymin>
			<xmax>1468</xmax>
			<ymax>294</ymax>
		</bndbox>
	</object>
	<object>
		<name>junction</name>
		<pose>Unspecified</pose>
		<truncated>0</truncated>
		<difficult>0</difficult>
		<bndbox>
			<xmin>1121</xmin>
			<ymin>267</ymin>
			<xmax>1145</xmax>
			<ymax>288</ymax>
		</bndbox>
	</object>
	<object>
		<name>junction</name>
		<pose>Unspecified</pose>
		<truncated>0</truncated>
		<difficult>0</difficult>
		<bndbox>
			<xmin>1122</xmin>
			<ymin>391</ymin>
			<xmax>1142</xmax>
			<ymax>411</ymax>
		</bndbox>
	</object>
	<object>
		<name>junction</name>
		<pose>Unspecified</pose>
		<truncated>0</truncated>
		<difficult>0</difficult>
		<bndbox>
			<xmin>1021</xmin>
			<ymin>391</ymin>
			<xmax>1049</xmax>
			<ymax>418</ymax>
		</bndbox>
	</object>
	<object>
		<name>junction</name>
		<pose>Unspecified</pose>
		<truncated>0</truncated>
		<difficult>0</difficult>
		<bndbox>
			<xmin>766</xmin>
			<ymin>286</ymin>
			<xmax>794</xmax>
			<ymax>314</ymax>
		</bndbox>
	</object>
	<object>
		<name>capacitor.unpolarized</name>
		<pose>Unspecified</pose>
		<truncated>0</truncated>
		<difficult>0</difficult>
		<bndbox>
			<xmin>730</xmin>
			<ymin>516</ymin>
			<xmax>818</xmax>
			<ymax>574</ymax>
		</bndbox>
	</object>
	<object>
		<name>text</name>
		<pose>Unspecified</pose>
		<truncated>0</truncated>
		<difficult>0</difficult>
		<bndbox>
			<xmin>299</xmin>
			<ymin>170</ymin>
			<xmax>464</xmax>
			<ymax>223</ymax>
		</bndbox>
	</object>
	<object>
		<name>text</name>
		<pose>Unspecified</pose>
		<truncated>0</truncated>
		<difficult>0</difficult>
		<bndbox>
			<xmin>16</xmin>
			<ymin>336</ymin>
			<xmax>155</xmax>
			<ymax>385</ymax>
		</bndbox>
	</object>
	<object>
		<name>text</name>
		<pose>Unspecified</pose>
		<truncated>0</truncated>
		<difficult>0</difficult>
		<bndbox>
			<xmin>807</xmin>
			<ymin>466</ymin>
			<xmax>945</xmax>
			<ymax>524</ymax>
		</bndbox>
	</object>
	<object>
		<name>text</name>
		<pose>Unspecified</pose>
		<truncated>0</truncated>
		<difficult>0</difficult>
		<bndbox>
			<xmin>838</xmin>
			<ymin>352</ymin>
			<xmax>954</xmax>
			<ymax>404</ymax>
		</bndbox>
	</object>
	<object>
		<name>text</name>
		<pose>Unspecified</pose>
		<truncated>0</truncated>
		<difficult>0</difficult>
		<bndbox>
			<xmin>1100</xmin>
			<ymin>122</ymin>
			<xmax>1260</xmax>
			<ymax>174</ymax>
		</bndbox>
	</object>
	<object>
		<name>text</name>
		<pose>Unspecified</pose>
		<truncated>0</truncated>
		<difficult>0</difficult>
		<bndbox>
			<xmin>1182</xmin>
			<ymin>300</ymin>
			<xmax>1272</xmax>
			<ymax>343</ymax>
		</bndbox>
	</object>
	<object>
		<name>text</name>
		<pose>Unspecified</pose>
		<truncated>0</truncated>
		<difficult>0</difficult>
		<bndbox>
			<xmin>818</xmin>
			<ymin>122</ymin>
			<xmax>915</xmax>
			<ymax>171</ymax>
		</bndbox>
	</object>
	<object>
		<name>junction</name>
		<pose>Unspecified</pose>
		<truncated>0</truncated>
		<difficult>0</difficult>
		<bndbox>
			<xmin>1031</xmin>
			<ymin>80</ymin>
			<xmax>1050</xmax>
			<ymax>98</ymax>
		</bndbox>
	</object>
	<object>
		<name>junction</name>
		<pose>Unspecified</pose>
		<truncated>0</truncated>
		<difficult>0</difficult>
		<bndbox>
			<xmin>1433</xmin>
			<ymin>93</ymin>
			<xmax>1457</xmax>
			<ymax>112</ymax>
		</bndbox>
	</object>
	<object>
		<name>text</name>
		<pose>Unspecified</pose>
		<truncated>0</truncated>
		<difficult>0</difficult>
		<bndbox>
			<xmin>1486</xmin>
			<ymin>292</ymin>
			<xmax>1618</xmax>
			<ymax>340</ymax>
		</bndbox>
	</object>
	<object>
		<name>text</name>
		<pose>Unspecified</pose>
		<truncated>0</truncated>
		<difficult>0</difficult>
		<bndbox>
			<xmin>1324</xmin>
			<ymin>528</ymin>
			<xmax>1405</xmax>
			<ymax>572</ymax>
		</bndbox>
	</object>
	<object>
		<name>text</name>
		<pose>Unspecified</pose>
		<truncated>0</truncated>
		<difficult>0</difficult>
		<bndbox>
			<xmin>1346</xmin>
			<ymin>580</ymin>
			<xmax>1402</xmax>
			<ymax>622</ymax>
		</bndbox>
	</object>
	<object>
		<name>text</name>
		<pose>Unspecified</pose>
		<truncated>0</truncated>
		<difficult>0</difficult>
		<bndbox>
			<xmin>1790</xmin>
			<ymin>433</ymin>
			<xmax>1973</xmax>
			<ymax>491</ymax>
		</bndbox>
	</object>
	<object>
		<name>text</name>
		<pose>Unspecified</pose>
		<truncated>0</truncated>
		<difficult>0</difficult>
		<bndbox>
			<xmin>1767</xmin>
			<ymin>518</ymin>
			<xmax>1896</xmax>
			<ymax>589</ymax>
		</bndbox>
	</object>
	<object>
		<name>text</name>
		<pose>Unspecified</pose>
		<truncated>0</truncated>
		<difficult>0</difficult>
		<bndbox>
			<xmin>1723</xmin>
			<ymin>675</ymin>
			<xmax>1909</xmax>
			<ymax>744</ymax>
		</bndbox>
	</object>
	<object>
		<name>terminal</name>
		<pose>Unspecified</pose>
		<truncated>0</truncated>
		<difficult>0</difficult>
		<bndbox>
			<xmin>1204</xmin>
			<ymin>759</ymin>
			<xmax>1298</xmax>
			<ymax>829</ymax>
		</bndbox>
	</object>
	<object>
		<name>diode</name>
		<pose>Unspecified</pose>
		<truncated>0</truncated>
		<difficult>0</difficult>
		<bndbox>
			<xmin>972</xmin>
			<ymin>534</ymin>
			<xmax>1089</xmax>
			<ymax>610</ymax>
		</bndbox>
	</object>
	<object>
		<name>diode</name>
		<pose>Unspecified</pose>
		<truncated>0</truncated>
		<difficult>0</difficult>
		<bndbox>
			<xmin>1088</xmin>
			<ymin>303</ymin>
			<xmax>1182</xmax>
			<ymax>359</ymax>
		</bndbox>
	</object>
	<object>
		<name>diode</name>
		<pose>Unspecified</pose>
		<truncated>0</truncated>
		<difficult>0</difficult>
		<bndbox>
			<xmin>849</xmin>
			<ymin>249</ymin>
			<xmax>926</xmax>
			<ymax>342</ymax>
		</bndbox>
	</object>
	<object>
		<name>diode</name>
		<pose>Unspecified</pose>
		<truncated>0</truncated>
		<difficult>0</difficult>
		<bndbox>
			<xmin>1342</xmin>
			<ymin>352</ymin>
			<xmax>1425</xmax>
			<ymax>437</ymax>
		</bndbox>
	</object>
	<object>
		<name>diode</name>
		<pose>Unspecified</pose>
		<truncated>0</truncated>
		<difficult>0</difficult>
		<bndbox>
			<xmin>1468</xmin>
			<ymin>351</ymin>
			<xmax>1548</xmax>
			<ymax>435</ymax>
		</bndbox>
	</object>
	<object>
		<name>diode</name>
		<pose>Unspecified</pose>
		<truncated>0</truncated>
		<difficult>0</difficult>
		<bndbox>
			<xmin>1475</xmin>
			<ymin>446</ymin>
			<xmax>1563</xmax>
			<ymax>529</ymax>
		</bndbox>
	</object>
	<object>
		<name>diode</name>
		<pose>Unspecified</pose>
		<truncated>0</truncated>
		<difficult>0</difficult>
		<bndbox>
			<xmin>1342</xmin>
			<ymin>443</ymin>
			<xmax>1418</xmax>
			<ymax>518</ymax>
		</bndbox>
	</object>
	<object>
		<name>junction</name>
		<pose>Unspecified</pose>
		<truncated>0</truncated>
		<difficult>0</difficult>
		<bndbox>
			<xmin>1323</xmin>
			<ymin>422</ymin>
			<xmax>1348</xmax>
			<ymax>448</ymax>
		</bndbox>
	</object>
	<object>
		<name>junction</name>
		<pose>Unspecified</pose>
		<truncated>0</truncated>
		<difficult>0</difficult>
		<bndbox>
			<xmin>1439</xmin>
			<ymin>337</ymin>
			<xmax>1466</xmax>
			<ymax>363</ymax>
		</bndbox>
	</object>
	<object>
		<name>junction</name>
		<pose>Unspecified</pose>
		<truncated>0</truncated>
		<difficult>0</difficult>
		<bndbox>
			<xmin>1562</xmin>
			<ymin>420</ymin>
			<xmax>1585</xmax>
			<ymax>442</ymax>
		</bndbox>
	</object>
	<object>
		<name>junction</name>
		<pose>Unspecified</pose>
		<truncated>0</truncated>
		<difficult>0</difficult>
		<bndbox>
			<xmin>1444</xmin>
			<ymin>522</ymin>
			<xmax>1467</xmax>
			<ymax>545</ymax>
		</bndbox>
	</object>
	<object>
		<name>junction</name>
		<pose>Unspecified</pose>
		<truncated>0</truncated>
		<difficult>0</difficult>
		<bndbox>
			<xmin>1619</xmin>
			<ymin>407</ymin>
			<xmax>1645</xmax>
			<ymax>436</ymax>
		</bndbox>
	</object>
	<object>
		<name>junction</name>
		<pose>Unspecified</pose>
		<truncated>0</truncated>
		<difficult>0</difficult>
		<bndbox>
			<xmin>1610</xmin>
			<ymin>277</ymin>
			<xmax>1627</xmax>
			<ymax>297</ymax>
		</bndbox>
	</object>
	<object>
		<name>junction</name>
		<pose>Unspecified</pose>
		<truncated>0</truncated>
		<difficult>0</difficult>
		<bndbox>
			<xmin>1435</xmin>
			<ymin>667</ymin>
			<xmax>1460</xmax>
			<ymax>690</ymax>
		</bndbox>
	</object>
	<object>
		<name>crossover</name>
		<pose>Unspecified</pose>
		<truncated>0</truncated>
		<difficult>0</difficult>
		<bndbox>
			<xmin>1231</xmin>
			<ymin>661</ymin>
			<xmax>1258</xmax>
			<ymax>682</ymax>
		</bndbox>
	</object>
	<object>
		<name>terminal</name>
		<pose>Unspecified</pose>
		<truncated>0</truncated>
		<difficult>0</difficult>
		<bndbox>
			<xmin>1721</xmin>
			<ymin>384</ymin>
			<xmax>1777</xmax>
			<ymax>475</ymax>
		</bndbox>
	</object>
	<object>
		<name>junction</name>
		<pose>Unspecified</pose>
		<truncated>0</truncated>
		<difficult>0</difficult>
		<bndbox>
			<xmin>771</xmin>
			<ymin>79</ymin>
			<xmax>792</xmax>
			<ymax>100</ymax>
		</bndbox>
	</object>
	<object>
		<name>junction</name>
		<pose>Unspecified</pose>
		<truncated>0</truncated>
		<difficult>0</difficult>
		<bndbox>
			<xmin>573</xmin>
			<ymin>80</ymin>
			<xmax>589</xmax>
			<ymax>97</ymax>
		</bndbox>
	</object>
	<object>
		<name>junction</name>
		<pose>Unspecified</pose>
		<truncated>0</truncated>
		<difficult>0</difficult>
		<bndbox>
			<xmin>569</xmin>
			<ymin>261</ymin>
			<xmax>592</xmax>
			<ymax>282</ymax>
		</bndbox>
	</object>
	<object>
		<name>junction</name>
		<pose>Unspecified</pose>
		<truncated>0</truncated>
		<difficult>0</difficult>
		<bndbox>
			<xmin>562</xmin>
			<ymin>462</ymin>
			<xmax>580</xmax>
			<ymax>481</ymax>
		</bndbox>
	</object>
	<object>
		<name>junction</name>
		<pose>Unspecified</pose>
		<truncated>0</truncated>
		<difficult>0</difficult>
		<bndbox>
			<xmin>300</xmin>
			<ymin>406</ymin>
			<xmax>320</xmax>
			<ymax>426</ymax>
		</bndbox>
	</object>
	<object>
		<name>junction</name>
		<pose>Unspecified</pose>
		<truncated>0</truncated>
		<difficult>0</difficult>
		<bndbox>
			<xmin>299</xmin>
			<ymin>462</ymin>
			<xmax>316</xmax>
			<ymax>478</ymax>
		</bndbox>
	</object>
	<object>
		<name>junction</name>
		<pose>Unspecified</pose>
		<truncated>0</truncated>
		<difficult>0</difficult>
		<bndbox>
			<xmin>313</xmin>
			<ymin>256</ymin>
			<xmax>330</xmax>
			<ymax>272</ymax>
		</bndbox>
	</object>
	<object>
		<name>junction</name>
		<pose>Unspecified</pose>
		<truncated>0</truncated>
		<difficult>0</difficult>
		<bndbox>
			<xmin>306</xmin>
			<ymin>304</ymin>
			<xmax>325</xmax>
			<ymax>322</ymax>
		</bndbox>
	</object>
	<object>
		<name>junction</name>
		<pose>Unspecified</pose>
		<truncated>0</truncated>
		<difficult>0</difficult>
		<bndbox>
			<xmin>551</xmin>
			<ymin>666</ymin>
			<xmax>570</xmax>
			<ymax>690</ymax>
		</bndbox>
	</object>
	<object>
		<name>junction</name>
		<pose>Unspecified</pose>
		<truncated>0</truncated>
		<difficult>0</difficult>
		<bndbox>
			<xmin>754</xmin>
			<ymin>663</ymin>
			<xmax>776</xmax>
			<ymax>685</ymax>
		</bndbox>
	</object>
	<object>
		<name>junction</name>
		<pose>Unspecified</pose>
		<truncated>0</truncated>
		<difficult>0</difficult>
		<bndbox>
			<xmin>1024</xmin>
			<ymin>660</ymin>
			<xmax>1044</xmax>
			<ymax>680</ymax>
		</bndbox>
	</object>
	<object>
		<name>junction</name>
		<pose>Unspecified</pose>
		<truncated>0</truncated>
		<difficult>0</difficult>
		<bndbox>
			<xmin>1249</xmin>
			<ymin>419</ymin>
			<xmax>1269</xmax>
			<ymax>441</ymax>
		</bndbox>
	</object>
	<object>
		<name>socket</name>
		<pose>Unspecified</pose>
		<truncated>0</truncated>
		<difficult>0</difficult>
		<bndbox>
			<xmin>161</xmin>
			<ymin>269</ymin>
			<xmax>277</xmax>
			<ymax>459</ymax>
		</bndbox>
	</object>
	<object>
		<name>terminal</name>
		<pose>Unspecified</pose>
		<truncated>0</truncated>
		<difficult>0</difficult>
		<bndbox>
			<xmin>126</xmin>
			<ymin>297</ymin>
			<xmax>161</xmax>
			<ymax>325</ymax>
		</bndbox>
	</object>
	<object>
		<name>terminal</name>
		<pose>Unspecified</pose>
		<truncated>0</truncated>
		<difficult>0</difficult>
		<bndbox>
			<xmin>118</xmin>
			<ymin>403</ymin>
			<xmax>151</xmax>
			<ymax>430</ymax>
		</bndbox>
	</object>
</annotation>
